django_openstack_auth_kerberos-0.3.0.dist-info/DESCRIPTION.rst
django_openstack_auth_kerberos-0.3.0.dist-info/METADATA
django_openstack_auth_kerberos-0.3.0.dist-info/RECORD
django_openstack_auth_kerberos-0.3.0.dist-info/WHEEL
django_openstack_auth_kerberos-0.3.0.dist-info/metadata.json
django_openstack_auth_kerberos-0.3.0.dist-info/pbr.json
django_openstack_auth_kerberos-0.3.0.dist-info/top_level.txt
openstack_auth_kerberos/__init__.py
openstack_auth_kerberos/plugin.py
openstack_auth_kerberos/urls.py
openstack_auth_kerberos/views.py
openstack_auth_kerberos/tests/__init__.py
openstack_auth_kerberos/tests/settings.py
openstack_auth_kerberos/tests/test_openstack_auth_kerberos.py
