Metadata-Version: 2.0
Name: django-openstack-auth-kerberos
Version: 0.3.0
Summary: Kerberos login to the OpenStack dashboard
Home-page: http://github.com/jamielennox/django-openstack-auth-kerberos
Author: OpenStack
Author-email: openstack-dev@lists.openstack.org
License: UNKNOWN
Platform: UNKNOWN
Classifier: Environment :: OpenStack
Classifier: Intended Audience :: Information Technology
Classifier: Intended Audience :: System Administrators
Classifier: License :: OSI Approved :: Apache Software License
Classifier: Operating System :: POSIX :: Linux
Classifier: Programming Language :: Python
Classifier: Programming Language :: Python :: 2
Classifier: Programming Language :: Python :: 2.7
Classifier: Programming Language :: Python :: 3
Classifier: Programming Language :: Python :: 3.4
Requires-Dist: Babel (>=0.9.6)
Requires-Dist: Django (>=1.4.2,<1.7)
Requires-Dist: django-openstack-auth (>=1.1.7,!=1.1.8)
Requires-Dist: keystoneauth1[kerberos] (>=2.1.0)
